cif2bin/__init__.py
cif2bin/main.py
cif2bin-0.0.6.dist-info/LICENSE
cif2bin-0.0.6.dist-info/METADATA
cif2bin-0.0.6.dist-info/WHEEL
cif2bin-0.0.6.dist-info/entry_points.txt
cif2bin-0.0.6.dist-info/top_level.txt
cif2bin-0.0.6.dist-info/RECORD
